parallelmediadownloader/__init__.py
parallelmediadownloader/exceptions.py
parallelmediadownloader/media_download_coroutine.py
parallelmediadownloader/media_file.py
parallelmediadownloader/media_filter.py
parallelmediadownloader/media_save_coroutine.py
parallelmediadownloader/modeia_download_result.py
parallelmediadownloader/parallel_media_download_coroutine.py
parallelmediadownloader/parallel_media_downloader.py
parallelmediadownloader/py.typed
tests/__init__.py
tests/conftest.py
tests/test_media_download_coroutine.py
tests/test_media_file.py
tests/test_media_filter.py
tests/test_media_save_coroutine.py
tests/test_parallel_media_downloader.py
tests/testlibraries/__init__.py
tests/testlibraries/instance_resource.py
parallelmediadownloader-0.1.0.dist-info/LICENSE
parallelmediadownloader-0.1.0.dist-info/METADATA
parallelmediadownloader-0.1.0.dist-info/WHEEL
parallelmediadownloader-0.1.0.dist-info/top_level.txt
parallelmediadownloader-0.1.0.dist-info/RECORD
