Metadata-Version: 2.1
Name: parallelmediadownloader
Version: 0.1.0
Summary: This project helps you to download media file.
Home-page: https://github.com/yukihiko-shinoda/parallel-media-downloader
Author: Yukihiko Shinoda
Author-email: yuk.hik.future@gmail.com
License: UNKNOWN
Keywords: parallel media download downloader image jpg jpeg png gif aiohttp
Platform: UNKNOWN
Classifier: Development Status :: 5 - Production/Stable
Classifier: Intended Audience :: Developers
Classifier: Intended Audience :: Information Technology
Classifier: License :: OSI Approved :: MIT License
Classifier: Natural Language :: English
Classifier: Operating System :: OS Independent
Classifier: Programming Language :: Python
Classifier: Programming Language :: Python :: 3
Classifier: Programming Language :: Python :: 3.7
Classifier: Programming Language :: Python :: 3.8
Classifier: Topic :: Internet :: WWW/HTTP
Classifier: Topic :: Multimedia :: Graphics
Classifier: Topic :: System :: Archiving
Classifier: Topic :: System :: Archiving :: Backup
Classifier: Typing :: Typed
Requires-Python: >=3.7
Requires-Dist: aiohttp
